{
  "AIR 6419 B40": "64x64",
  "AIR 6419 B78A": "64x64",
  "RRU5904": "4x4",
  "RRU5919": "2x2",
  "RRU5901": "4x4",
  "RRU5304w": "4x4",
  "RRU5304": "4x4",
  "RRU5305": "4x4",
  "RRU5309": "4x4",
  "RRU5502": "4x4",
  "RRU3281": "4x4",
  "RRU5503": "4x4",
  "RRU5508": "4x4",
  "RRU3938": "2x2",
  "RRU5258": "4x4",
  "RRU5258p": "4x4",
  "RRU3268": "2x2",
  "RRU3268e": "2x2",
  "RRU3826": "2x2",
  "RRU3936": "2x2",
  "RRU3953": "2x2",
  "RRU3971": "2x2",
  "RRU5818w": "8x8",
  "AAU5636w": "64x64",
  "RRU5505": "4x4",
  "RRUS 12 B7": "2x2",
  "RRU3971 1800M WD5M18397100": "2x2",
  "RRU5301": "4x4",
  "hRRU5301": "2x2",
  "RRU5522w": "4x4",
  "Radio 2217 B7": "2x2",
  "Radio 2217 B28A": "2x2",
  "Radio 2217 B28B": "2x2",
  "Radio 2217 B1": "2x2",
  "Radio 2217 B3": "2x2",
  "Radio 2217": "2x2",
  "Radio 2219": "2x2",
  "Radio 2219 B1": "2x2",
  "Radio 2219 B3": "2x2",
  "Radio 2219 B28": "2x2",
  "Radio 2219 B7": "2x2",
  "mRRUS 12 B3 (*)": "2x2",
  "Radio 2219 B5": "2x2",
  "Radio 4415": "4x4",
  "Radio 4415 B7": "4x4",
  "Radio 4415 B3": "4x4",
  "Radio 4416": "4x4",
  "Radio 4422": "4x4",
  "Radio 4443": "4x4",
  "Radio 4449": "4x4",
  "Radio 4471 B1": "4x4",
  "Radio 4480": "4x4",
  "Radio 4490": "4x4",
  "Radio 8843": "8x8",
  "Radio 2271": "2x2",
  "AIR 5121": "4x4",
  "AIR 6488": "8x8",
  "AIR 3227 B78W": "32x32",
  "AIR 3258": "32x32",
  "AIR 3268": "32x32",
  "AIR 3219 B78AA": "32x32",
  "AIR 6428": "8x8",
  "AIR 6419 B42": "64x64",
  "RRUS 01 B1": "1x2",
  "RRUS 01 B5": "1x2",
  "RRUS 02 B1": "2x2",
  "RRUS 11 B1": "2x2",
  "RRUS 12 B1": "2x2",
  "RRUS 13 B1": "2x2",
  "RRUS 32 B1": "4x4",
  "RRUS 32 B5": "4x4",
  "dTRU-8": "1x1",
  "dTRU": "1x1",
  "AAU5331w": "8x8",
  "AAU5336w": "8x8",
  "AAU5336m": "32x32",
  "AAU5613": "8x8",
  "AAU5639": "32x32",
  "AAU5649": "64x64",
  "AAU5339w": "32x32",
  "AHFIG": "2x2",
  "FRGY": "4x4",
  "FZHF": "8x8",
  "FRIG": "2x2",
  "FRBC": "8x8",
  "FRPB": "2x2",
  "R8855": "4x4",
  "R8868": "8x8",
  "R8884": "8x8",
  "R8862A S8500": "2x2",
  "ZXSDR R8862A S8500": "2x2",
  "NOVA 227 banda 40": "2x2",
  "✨ AAU5636": "64x64",
  "✨ AHEGC": "4x4",
  "✨ AIR 6449 B78W": "64x64",
  "✨ AQQN": "64x64",
  "✨ ARGA": "6x6",
  "✨ AirScale Dual RRH 4T4R B1/3 320W": "4x4",
  "✨ AirScale RFM 6T6R B3 480 W": "6x6",
  "✨ FRHA": "3x6",
  "✨ FRPA": "6x6",
  "✨ FXEA": "3x3",
  "✨ FXED": "2x2",
  "✨ KRC 161 253/1 - RRUS 11 B7": "2x2",
  "✨ KRC 161 282/2": "2x2",
  "✨ KRC 161 325/2": "2x2",
  "✨ RRU3201 - WD5MIRU187D": "2x2",
  "✨ RRU3262 WD5M07326200": "2x4",
  "✨ RRU3268 WD5M07LRRU03": "2x2",
  "✨ RRU3268 WD5MLRUD870": "2x2",
  "✨ RRU3281 WD5M26328100": "4x4",
  "✨ RRU3908 MRRU-WD5M1A2DD1": "2x2",
  "✨ RRU3908 MRRU-WD5MJRUCC50": "2x2",
  "✨ RRU3938-WD5M18393800": "2x2",
  "✨ RRU3952 850M – WD5M85395200": "2x4",
  "✨ RRU5903": "2x4",
  "✨ RRU5904 - WD5M215904GB": "4x4",
  "✨ RRU5905w": "2x2",
  "✨ RRU5909": "2x2",
  "✨ Radio 2212": "2x2",
  "✨ Radio 2271 B28": "2x2",
  "✨ Radio 4490 B1 B3": "4x4",
  "✨ WD5MMRFU73A": "2x2",
  "✨ FRHC": "6x6",
  "✨ FXCB": "2x2",
  "✨ Flexi 3-sector RF Module 2100 (FRGT)": "2x2",
  "✨ KRC 118 46/2": "2x2",
  "✨ KRC 161 134/1": "2x2",
  "✨ KRC 161 134/5": "2x2",
  "✨ RRU3936 WD5M85393600": "2x2",
  "✨ Radio 2271 B1": "2x2"
}
